{"cameraMode":{"drawMode":0,"name":"Shaded","section":"Shading Mode"},"sceneLighting":false,"audioPlay":false,"sceneViewState":{"showFog":true,"showMaterialUpdate":false,"showSkybox":false,"showFlares":true,"showImageEffects":true,"showParticleSystems":true},"in2DMode":false,"pivot":{"x":-661.96484375,"y":773.5499877929688,"z":430.5669860839844},"rotation":{"x":-0.14736178517341615,"y":0.6945609450340271,"z":-0.14868804812431336,"w":-0.6883243918418884},"size":1.8468480110168458,"orthographic":false}